soapsnow/__init__.py
soapsnow/soapsnow.py
soapsnow-0.1.3.dist-info/LICENSE
soapsnow-0.1.3.dist-info/METADATA
soapsnow-0.1.3.dist-info/WHEEL
soapsnow-0.1.3.dist-info/top_level.txt
soapsnow-0.1.3.dist-info/RECORD
