Metadata-Version: 2.1
Name: soapsnow
Version: 0.1.3
Summary: A simple Python library for interacting with ServiceNow's API
Home-page: https://github.com/xthehatterx/soapsnow
Author: Ezequiel M. Iglesias
Author-email: ezequiel.m.iglesias@gmail.com
License: MIT
Platform: UNKNOWN
Classifier: Programming Language :: Python :: 3
Classifier: License :: OSI Approved :: MIT License
Classifier: Operating System :: OS Independent
Requires-Python: >=3.6
Requires-Dist: requests
